locomotivecms/__init__.py
locomotivecms/main.py
locomotivecms-0.0.3.dist-info/METADATA
locomotivecms-0.0.3.dist-info/WHEEL
locomotivecms-0.0.3.dist-info/RECORD
