Metadata-Version: 2.3
Name: locomotivecms
Version: 0.0.3
Summary: Client for locomotivecms
Project-URL: Homepage, https://github.com/shopinvader/locomotivecms-python-client/
Author-email: Akretion <contact@akretion.com>
Requires-Dist: requests
